pyamsd/__init__.py
pyamsd/__main__.py
pyamsd/api.py
pyamsd/util.py
pyamsd/commands/__init__.py
pyamsd/commands/check.py
pyamsd/commands/copy_media.py
pyamsd/commands/to_csv.py
pyamsd/commands/upload_media.py
pyamsd-1.0.0.dist-info/LICENSE
pyamsd-1.0.0.dist-info/METADATA
pyamsd-1.0.0.dist-info/WHEEL
pyamsd-1.0.0.dist-info/entry_points.txt
pyamsd-1.0.0.dist-info/top_level.txt
pyamsd-1.0.0.dist-info/RECORD
